README.md
pyproject.toml
setup.py
Tintegrals/OneLoop.py
Tintegrals/T111.py
Tintegrals/T111113.py
Tintegrals/T1111134.py
Tintegrals/T11113.py
Tintegrals/T111133.py
Tintegrals/T1111334.py
Tintegrals/T111134.py
Tintegrals/T1113.py
Tintegrals/T11133.py
Tintegrals/T111333.py
Tintegrals/T1113334.py
Tintegrals/T111334.py
Tintegrals/T1113344.py
Tintegrals/T11134.py
Tintegrals/T113.py
Tintegrals/T1133.py
Tintegrals/T11334.py
Tintegrals/T113344.py
Tintegrals/T1134.py
Tintegrals/T134.py
Tintegrals/Talt.py
Tintegrals/__init__.py
Tintegrals/config.py
Tintegrals.egg-info/PKG-INFO
Tintegrals.egg-info/SOURCES.txt
Tintegrals.egg-info/dependency_links.txt
Tintegrals.egg-info/requires.txt
Tintegrals.egg-info/top_level.txt
tests/test_Tint.py