Metadata-Version: 2.4
Name: Tintegrals
Version: 1.1
Author-email: Henning Bahl <bahl@thphys.uni-heidelberg.de>, Johannes Braathen <johannes.braathen@desy.de>, Martin Gabelmann <martin.gabelmann@desy.de>
Requires-Python: >=3.5
Requires-Dist: numpy>=1.13.0
Requires-Dist: scipy
Requires-Dist: mpmath
Requires-Dist: sympy
